geovisio_cli/__init__.py
geovisio_cli/__main__.py
geovisio_cli/auth.py
geovisio_cli/exception.py
geovisio_cli/main.py
geovisio_cli/model.py
geovisio_cli/utils.py
geovisio_cli/sequences/__init__.py
geovisio_cli/sequences/status.py
geovisio_cli/sequences/upload.py
geovisio_cli/sequences/external_metadata/__init__.py
geovisio_cli/sequences/external_metadata/csv_metadata.py
geovisio_cli/sequences/external_metadata/utils.py
geovisio_cli/sequences/process/__init__.py
geovisio_cli/sequences/process/standard.py
geovisio_cli-0.3.14.dist-info/entry_points.txt
geovisio_cli-0.3.14.dist-info/LICENSE
geovisio_cli-0.3.14.dist-info/WHEEL
geovisio_cli-0.3.14.dist-info/METADATA
geovisio_cli-0.3.14.dist-info/RECORD
